text2speech/__init__.py
text2speech/module.py
text2speech_api/__init__.py
text2speech_api/module.py
text2video/__init__.py
text2video/module.py
text2speech_api-0.0.1.dist-info/METADATA
text2speech_api-0.0.1.dist-info/WHEEL
text2speech_api-0.0.1.dist-info/top_level.txt
text2speech_api-0.0.1.dist-info/RECORD
