Metadata-Version: 2.1
Name: text2speech_api
Version: 0.0.1
Summary: Utils for text2speech tts generation
Author-email: dingo0927@126.com
Keywords: text,speech,generation
Classifier: Development Status :: 3 - Alpha
Classifier: Intended Audience :: Developers
Classifier: Topic :: Software Development :: Build Tools
Classifier: License :: OSI Approved :: MIT License
Requires-Python: >=3.4
